audio_tuner_gui/__init__.py
audio_tuner_gui/analysis.py
audio_tuner_gui/common.py
audio_tuner_gui/display.py
audio_tuner_gui/export.py
audio_tuner_gui/file_selector.py
audio_tuner_gui/log_viewer.py
audio_tuner_gui/option_panel.py
audio_tuner_gui/player.py
audio_tuner_gui/icons/audio_tuner_icon.ico
audio_tuner_gui/icons/audio_tuner_icon.svg
audio_tuner_gui/icons/audio_tuner_icon_hires.svg
audio_tuner_gui/icons/audio_tuner_logo_dark.svg
audio_tuner_gui/icons/audio_tuner_logo_light.svg
audio_tuner_gui/icons/black-logo.svg
audio_tuner_gui/icons/folder.png
audio_tuner_gui/icons/gpl-v3-logo_red.svg
audio_tuner_gui/icons/gpl-v3-logo_white.svg
audio_tuner_gui/icons/preferences-other.png
audio_tuner_gui/icons/process-stop.png
audio_tuner_gui/icons/white-logo.svg
audio_tuner_gui/scripts/__init__.py
audio_tuner_gui/scripts/tuner_gui.py
audio_tuner_gui-0.10.0.dist-info/METADATA
audio_tuner_gui-0.10.0.dist-info/WHEEL
audio_tuner_gui-0.10.0.dist-info/entry_points.txt
audio_tuner_gui-0.10.0.dist-info/licenses/COPYING
audio_tuner_gui-0.10.0.dist-info/RECORD
