Metadata-Version: 2.4
Name: audio-tuner-gui
Version: 0.10.0
Summary: Graphical interface for Audio Tuner
Project-URL: Homepage, https://codeberg.org/bluesloth/audio_tuner
Project-URL: Repository, https://codeberg.org/bluesloth/audio_tuner.git
Project-URL: Issues, https://codeberg.org/bluesloth/audio_tuner/issues
Project-URL: Documentation, https://audio-tuner.readthedocs.io/en/latest/
Author-email: Jessie Blue Cassell <bluesloth600@gmail.com>
License-File: COPYING
Keywords: audio,music,pitch shift,player,tempo shift,tuning
Classifier: License :: OSI Approved :: GNU General Public License v3 or later (GPLv3+)
Classifier: Operating System :: OS Independent
Classifier: Programming Language :: Python :: 3
Requires-Python: >=3.11
Requires-Dist: audio-tuner
Requires-Dist: pyqt6
Requires-Dist: python-mpv
